{
  "credit": "Made with Blockbench",
  "parent": "builtin/entity",
  "texture_size": [
    128,
    128
  ],
  "display": {
    "thirdperson_righthand": {
      "scale": [
        0.25,
        0.25,
        0.25
      ]
    },
    "thirdperson_lefthand": {
      "scale": [
        0.25,
        0.25,
        0.25
      ]
    },
    "firstperson_righthand": {
      "scale": [
        0.25,
        0.25,
        0.25
      ]
    },
    "firstperson_lefthand": {
      "scale": [
        0.25,
        0.25,
        0.25
      ]
    },
    "ground": {
      "scale": [
        0.25,
        0.25,
        0.25
      ]
    },
    "gui": {
      "rotation": [
        0,
        140,
        0
      ],
      "translation": [
        0,
        -9.5,
        -2.75
      ],
      "scale": [
        0.5,
        0.5,
        0.5
      ]
    },
    "head": {
      "translation": [
        0,
        7,
        0
      ],
      "scale": [
        0.25,
        0.25,
        0.25
      ]
    },
    "fixed": {
      "translation": [
        0,
        -9,
        -2.75
      ],
      "scale": [
        0.5,
        0.5,
        0.5
      ]
    }
  }
}